match_srt/__init__.py
match_srt/match_srt.py
match_srt-0.1.0.dist-info/entry_points.txt
match_srt-0.1.0.dist-info/WHEEL
match_srt-0.1.0.dist-info/METADATA
match_srt-0.1.0.dist-info/RECORD
