Metadata-Version: 2.1
Name: match-srt
Version: 0.1.0
Summary: 
Home-page: https://github.com/urfu-online/match_srt
Author: MasterGowen
Author-email: mastergowen@gmail.com
Requires-Python: >=3.10,<4.0
Classifier: Programming Language :: Python :: 3
Classifier: Programming Language :: Python :: 3.10
Requires-Dist: click (>=8.1.3,<9.0.0)
Requires-Dist: opencv-python (>=4.7.0,<5.0.0)
Requires-Dist: pysrt (>=1.1.2,<2.0.0)
Requires-Dist: rich (>=13.3.3,<14.0.0)
Project-URL: Repository, https://github.com/urfu-online/match_srt
